audioaliasingmetrics/__init__.py
audioaliasingmetrics/sinad.py
audioaliasingmetrics/snr.py
audioaliasingmetrics/utils.py
pyaudioaliasingmetrics-0.1.0.dist-info/LICENSE
pyaudioaliasingmetrics-0.1.0.dist-info/METADATA
pyaudioaliasingmetrics-0.1.0.dist-info/WHEEL
pyaudioaliasingmetrics-0.1.0.dist-info/top_level.txt
pyaudioaliasingmetrics-0.1.0.dist-info/RECORD
