Metadata-Version: 2.1
Name: pyaudioaliasingmetrics
Version: 0.1.0
Summary: Computes SNR and SINAD from spectral data
Home-page: https://github.com/maxmarsc/pyaudioaliasingmetrics
Author: Maxime COUTANT
Author-email: maxime.coutant@protonmail.com
License: MIT
Platform: UNKNOWN
Classifier: Development Status :: 3 - Alpha
Classifier: Intended Audience :: Science/Research
Classifier: License :: OSI Approved :: MIT License
Classifier: Programming Language :: Python :: 3
Classifier: Topic :: Multimedia :: Sound/Audio :: Analysis
License-File: LICENSE
Requires-Dist: numba
Requires-Dist: numpy
